AUTHORS
LICENSE
MANIFEST.in
README
README.rst
RELEASE-NOTES.txt
setup.py
anyvcs/__init__.py
anyvcs/common.py
anyvcs/git.py
anyvcs/hashdict.py
anyvcs/hg.py
anyvcs/svn.py
anyvcs/version.py
anyvcs.egg-info/PKG-INFO
anyvcs.egg-info/SOURCES.txt
anyvcs.egg-info/dependency_links.txt
anyvcs.egg-info/top_level.txt