Metadata-Version: 1.1
Name: anyvcs
Version: 1.4.0
Summary: An abstraction layer for multiple version control systems.
Home-page: https://github.com/ScottDuckworth/python-anyvcs
Author: Scott Duckworth
Author-email: sduckwo@clemson.edu
License: BSD
Platform: UNKNOWN
Classifier: Intended Audience :: Developers
Classifier: License :: OSI Approved :: BSD License
Classifier: Operating System :: POSIX
Classifier: Programming Language :: Python
Classifier: Programming Language :: Python :: 2.6
Classifier: Programming Language :: Python :: 2.7
Classifier: Programming Language :: Python :: 3
Classifier: Topic :: Software Development :: Version Control
